quasimodo/__init__.py
quasimodo/amqp.py
quasimodo/base.py
quasimodo/hunchback.py
quasimodo/mqtt_websocket.py
quasimodo/stubs.py
quasimodo-0.8.0.dist-info/METADATA
quasimodo-0.8.0.dist-info/WHEEL
quasimodo-0.8.0.dist-info/entry_points.txt
quasimodo-0.8.0.dist-info/licenses/COPYING
quasimodo-0.8.0.dist-info/RECORD
