Metadata-Version: 2.4
Name: quasimodo
Version: 0.8.0
Summary: AMQP and MQTT over WebSocket Queue Clients
Author-email: doubleO8 <wb008@hdm-stuttgart.de>
License-Expression: GPL-2.0-only
License-File: COPYING
Requires-Python: >=3.6.8
Requires-Dist: paho-mqtt>=1.6.1
Requires-Dist: pika>=1.2.1
